gradio_terminal/__init__.py
gradio_terminal/terminal.py
gradio_terminal-1.1.0.dist-info/licenses/LICENSE
gradio_terminal-1.1.0.dist-info/METADATA
gradio_terminal-1.1.0.dist-info/WHEEL
gradio_terminal-1.1.0.dist-info/top_level.txt
gradio_terminal-1.1.0.dist-info/RECORD
