Metadata-Version: 2.4
Name: gradio-terminal
Version: 1.1.0
Summary: A Gradio component that provides a fully functional terminal using xterm.js and PTY
Author: Po-Hsuan Huang
Author-email: Po-Hsuan Huang <aben20807@gmail.com>
License: Apache-2.0
Project-URL: Homepage, https://github.com/aben20807/gradio-terminal
Project-URL: Repository, https://github.com/aben20807/gradio-terminal
Project-URL: Issues, https://github.com/aben20807/gradio-terminal/issues
Keywords: gradio,terminal,xterm,pty,shell
Classifier: Development Status :: 3 - Alpha
Classifier: Intended Audience :: Developers
Classifier: License :: OSI Approved :: Apache Software License
Classifier: Operating System :: POSIX :: Linux
Classifier: Programming Language :: Python :: 3
Classifier: Programming Language :: Python :: 3.8
Classifier: Programming Language :: Python :: 3.9
Classifier: Programming Language :: Python :: 3.10
Classifier: Programming Language :: Python :: 3.11
Classifier: Programming Language :: Python :: 3.12
Requires-Python: >=3.8
License-File: LICENSE
Requires-Dist: gradio>=6.3.0
Requires-Dist: flask>=3.1.2
Requires-Dist: flask-socketio>=5.6.0
Provides-Extra: dev
Requires-Dist: pytest>=7.0.0; extra == "dev"
Requires-Dist: black>=22.0.0; extra == "dev"
Requires-Dist: flake8>=4.0.0; extra == "dev"
Dynamic: author
Dynamic: license-file
Dynamic: requires-python
